[
  {
    "name": "integrator",
    "root": ".",
    "status": "active",
    "priority": "p0",
    "entrypoint": "python -m integrator",
    "tags": ["cli", "hub", "automation"]
  },
  {
    "name": "localai",
    "root": "vault/Projects/LocalAI",
    "status": "active",
    "priority": "p0",
    "entrypoint": "LocalAI/assistant",
    "tags": ["rag", "kb", "ssot"]
  },
  {
    "name": "localai-assistant",
    "root": "LocalAI/assistant",
    "status": "active",
    "priority": "p0",
    "entrypoint": "python LocalAI/assistant/mcp_server.py",
    "tags": ["assistant", "mcp", "rag"]
  },
  {
    "name": "vpn-manager",
    "root": "vault/Projects/vpn-manager",
    "status": "active",
    "priority": "p2",
    "entrypoint": "vault/Projects/vpn-manager",
    "tags": ["vpn", "fedora", "cpp"]
  }
]
